mo_divide/__init__.py
mo_divide/divide.py
mo_divide-0.1.1.dist-info/METADATA
mo_divide-0.1.1.dist-info/WHEEL
mo_divide-0.1.1.dist-info/top_level.txt
mo_divide-0.1.1.dist-info/RECORD
