Metadata-Version: 2.1
Name: mo_divide
Version: 0.1.1
Summary: Default template for PDM package
Author-email: Mingk42 <xoals123456t@gmail.com>
License: MIT
Project-URL: Homepage, https://github.com/Mingk42/mo_divide
Requires-Python: >=3.8
